boring_math/number_theory/__init__.py
boring_math/number_theory/py.typed
boring_math_number_theory-2.0.0.dist-info/licenses/LICENSE
boring_math_number_theory-2.0.0.dist-info/WHEEL
boring_math_number_theory-2.0.0.dist-info/METADATA
boring_math_number_theory-2.0.0.dist-info/RECORD
